main.py
setup.py
tiketoken.egg-info/PKG-INFO
tiketoken.egg-info/SOURCES.txt
tiketoken.egg-info/dependency_links.txt
tiketoken.egg-info/requires.txt
tiketoken.egg-info/top_level.txt